kitikiplot/core/__init__.py
kitikiplot/core/kitiki_cell.py
kitikiplot/core/kitiki_color_config.py
kitikiplot/core/kitikiplot.py
kitikiplot/ecology/grid.py
kitikiplot/ecology/linear.py
kitikiplot/genomics/__init__.py
kitikiplot/genomics/grid.py
kitikiplot/genomics/linear.py
kitikiplot-1.0.0.dist-info/LICENSE
kitikiplot-1.0.0.dist-info/METADATA
kitikiplot-1.0.0.dist-info/WHEEL
kitikiplot-1.0.0.dist-info/RECORD
