Metadata-Version: 2.3
Name: kitikiplot
Version: 1.0.0
Summary: A Python library to visualize categorical sliding window data.
License: MIT
Keywords: sliding window,sequential,time-series,genome,categorical data
Author: Boddu Sri Pavan
Author-email: boddusripavan111@gmail.com
Requires-Python: >=3.11
Classifier: License :: OSI Approved :: MIT License
Classifier: Operating System :: OS Independent
Classifier: Programming Language :: Python :: 3
Classifier: Programming Language :: Python :: 3.11
Classifier: Programming Language :: Python :: 3.12
Classifier: Programming Language :: Python :: 3.13
Classifier: Topic :: Scientific/Engineering :: Visualization
Requires-Dist: biopython
Requires-Dist: matplotlib
Requires-Dist: numpy
Requires-Dist: pandas
Project-URL: Bug Tracker, https://github.com/BodduSriPavan-111/kitikiplot/issues
Project-URL: Documentation, https://github.com/BodduSriPavan-111/kitikiplot/wiki
Project-URL: Repository, https://github.com/BodduSriPavan-111/kitikiplot
Project-URL: Source Code, https://github.com/BodduSriPavan-111/kitikiplot
